odoo/addons/stock_search_supplierinfo_code/README.rst
odoo/addons/stock_search_supplierinfo_code/__init__.py
odoo/addons/stock_search_supplierinfo_code/__manifest__.py
odoo/addons/stock_search_supplierinfo_code/i18n/es.po
odoo/addons/stock_search_supplierinfo_code/i18n/it.po
odoo/addons/stock_search_supplierinfo_code/i18n/stock_search_supplierinfo_code.pot
odoo/addons/stock_search_supplierinfo_code/readme/CONTRIBUTORS.md
odoo/addons/stock_search_supplierinfo_code/readme/DESCRIPTION.md
odoo/addons/stock_search_supplierinfo_code/static/description/icon.png
odoo/addons/stock_search_supplierinfo_code/static/description/index.html
odoo/addons/stock_search_supplierinfo_code/views/stock_picking.xml
odoo_addon_stock_search_supplierinfo_code-17.0.1.0.0.2.dist-info/METADATA
odoo_addon_stock_search_supplierinfo_code-17.0.1.0.0.2.dist-info/WHEEL
odoo_addon_stock_search_supplierinfo_code-17.0.1.0.0.2.dist-info/top_level.txt
odoo_addon_stock_search_supplierinfo_code-17.0.1.0.0.2.dist-info/RECORD
