Metadata-Version: 2.1
Name: odoo-addon-stock_search_supplierinfo_code
Version: 17.0.1.0.0.2
Requires-Python: >=3.10
Requires-Dist: odoo>=17.0a,<17.1dev
Summary: Allows to search for picking from supplierinfo code
Home-page: https://github.com/OCA/stock-logistics-warehouse
License: AGPL-3
Author: Akretion,Odoo Community Association (OCA)
Author-email: support@odoo-community.org
Classifier: Programming Language :: Python
Classifier: Framework :: Odoo
Classifier: Framework :: Odoo :: 17.0
Classifier: License :: OSI Approved :: GNU Affero General Public License v3
